aigroup_quant_mcp-1.0.28.dist-info/licenses/LICENSE
quantanalyzer/__init__.py
quantanalyzer/mcp.py
quantanalyzer/backtest/__init__.py
quantanalyzer/backtest/engine.py
quantanalyzer/data/__init__.py
quantanalyzer/data/converter.py
quantanalyzer/data/loader.py
quantanalyzer/data/processor.py
quantanalyzer/factor/__init__.py
quantanalyzer/factor/alpha158.py
quantanalyzer/factor/evaluator.py
quantanalyzer/factor/library.py
quantanalyzer/mcp/__init__.py
quantanalyzer/mcp/__main__.py
quantanalyzer/mcp/errors.py
quantanalyzer/mcp/handlers.py
quantanalyzer/mcp/resources.py
quantanalyzer/mcp/schemas.py
quantanalyzer/mcp/server.py
quantanalyzer/mcp/utils.py
quantanalyzer/model/__init__.py
quantanalyzer/model/deep_models.py
quantanalyzer/model/trainer.py
aigroup_quant_mcp-1.0.28.dist-info/METADATA
aigroup_quant_mcp-1.0.28.dist-info/WHEEL
aigroup_quant_mcp-1.0.28.dist-info/entry_points.txt
aigroup_quant_mcp-1.0.28.dist-info/top_level.txt
aigroup_quant_mcp-1.0.28.dist-info/RECORD
