Metadata-Version: 2.4
Name: aigroup-quant-mcp
Version: 1.0.28
Summary: AI Group Quantitative Analysis MCP Service - Machine Learning Models (No Torch Required)
Author-email: AI Group <ai.group@example.com>
License-Expression: MIT
Classifier: Development Status :: 4 - Beta
Classifier: Intended Audience :: Developers
Classifier: Intended Audience :: Financial and Insurance Industry
Classifier: Intended Audience :: Science/Research
Classifier: Programming Language :: Python :: 3
Classifier: Programming Language :: Python :: 3.8
Classifier: Programming Language :: Python :: 3.9
Classifier: Programming Language :: Python :: 3.10
Classifier: Programming Language :: Python :: 3.11
Classifier: Programming Language :: Python :: 3.12
Classifier: Topic :: Scientific/Engineering :: Artificial Intelligence
Classifier: Topic :: Scientific/Engineering :: Information Analysis
Classifier: Topic :: Office/Business :: Financial :: Investment
Classifier: Topic :: Software Development :: Libraries :: Python Modules
Classifier: Operating System :: OS Independent
Classifier: Natural Language :: English
Classifier: Natural Language :: Chinese (Simplified)
Requires-Python: >=3.8
License-File: LICENSE
Requires-Dist: pandas>=2.0.0
Requires-Dist: numpy>=1.24.0
Requires-Dist: scipy>=1.10.0
Requires-Dist: mcp>=1.0.0
Requires-Dist: lightgbm>=4.0.0
Requires-Dist: xgboost>=2.0.0
Requires-Dist: scikit-learn>=1.3.0
Provides-Extra: dl
Requires-Dist: torch>=2.0.0; extra == "dl"
Provides-Extra: full
Requires-Dist: lightgbm>=4.0.0; extra == "full"
Requires-Dist: xgboost>=2.0.0; extra == "full"
Requires-Dist: scikit-learn>=1.3.0; extra == "full"
Requires-Dist: torch>=2.0.0; extra == "full"
Provides-Extra: viz
Requires-Dist: matplotlib>=3.7.0; extra == "viz"
Provides-Extra: dev
Requires-Dist: pytest>=7.4.0; extra == "dev"
Dynamic: license-file
